{
  "close_reason": "Extracted map_keyring_error and map_join_error helpers",
  "closed_at": "2026-06-16T18:40:47Z",
  "compaction_level": 0,
  "content_hash": "320be5707a924693d96816df9aa698cc73860c596c6a5487259ed8cedb2e0ff0",
  "created_at": "2026-05-08T02:03:39Z",
  "created_by": "Mark Atwood",
  "description": "secretx-keyring/src/lib.rs has the closure pattern `|e| SecretError::Backend { backend: \"keyring\", source: e.into() }` repeated 4 times: lines 118-121, 129-132, 136-139, 160-163, 169-172, 176-179. Each invocation differs only in the source binding name and the immediately surrounding context.\n\nThe sibling crate secretx-wolfhsm extracts this to a helper:\n```rust\nfn join_err(e: tokio::task::JoinError) -> SecretError {\n    SecretError::Backend { backend: BACKEND, source: e.into() }\n}\n```\n\u2026called as `.map_err(join_err)?`.\n\nFor keyring, two helpers (or one generic) would cover the cases:\n```rust\nfn backend_err<E: std::error::Error + Send + Sync + 'static>(e: E) -> SecretError {\n    SecretError::Backend { backend: BACKEND, source: Box::new(e) }\n}\n```\n\nNet change: eliminates ~12 lines of duplication, makes the get/put method bodies show only their domain logic. Reads as net-positive after the change.\n\nThis is taste-adjacent but the duplication count justifies the abstraction \u2014 net negative abstraction concern (Section 3 of /review-myoss) does not apply because the helper saves more lines than it adds.",
  "ephemeral": 0,
  "id": "crate-secretsx-t2qi.11",
  "is_template": 0,
  "issue_type": "chore",
  "metadata": {},
  "no_history": 0,
  "owner": "mark@reviewcommit.com",
  "pinned": 0,
  "priority": 3,
  "status": "closed",
  "timeout_ns": 0,
  "title": "Repeated SecretError::Backend{...e.into()} mapping pattern \u2014 extract helper",
  "updated_at": "2026-06-16T18:40:47Z",
  "dependencies": [
    {
      "created_at": "2026-05-07T19:03:38Z",
      "created_by": "Mark Atwood",
      "depends_on_id": "crate-secretsx-t2qi",
      "metadata": {},
      "type": "parent-child"
    }
  ]
}
