{
  "assignee": "Mark Atwood",
  "close_reason": "Closed",
  "closed_at": "2026-06-16T15:02:23Z",
  "compaction_level": 0,
  "content_hash": "12ad977c64811e8ee4aa4038cd37185a753d9f695fafe1592bc7eb5cafec89fb",
  "created_at": "2026-05-08T01:34:49Z",
  "created_by": "Mark Atwood",
  "description": "src/lib.rs:236-247 maps HTTP 401 to SecretError::Unavailable with hint 'GCP_ACCESS_TOKEN may have expired; reconstruct the backend with a fresh token'.\n\nBut secretx-core/src/lib.rs:976-983 documents Backend as the variant for 'authentication failure, permission denied' and Unavailable as 'retrying may succeed' with 'retry with back-off'. Plain back-off retry on 401 will not succeed without operator action (new token); the type-level signal 'Unavailable -> retry with backoff' misleads programmatic callers.\n\nThe deliberate justification (token-expiry recovery via reconstruct) is operationally valid but conflicts with the documented contract. Two paths to resolve:\n  (a) Map 401 -> Backend (strict contract conformance). Operators read the error message; programmatic callers correctly abort.\n  (b) Update secretx-core's Unavailable doc to explicitly cover 'caller may recover by reconstructing with new credentials' \u2014 making this case a sanctioned use of Unavailable.\n\nUntil resolved, callers that retry-on-Unavailable in a tight loop will burn through GCP rate limits with the same expired token.\n\nCross-crate aspect: the contract lives in secretx-core; the deviation lives here. Either change requires touching one or the other.\n\nTrigger: any 401 from GCP SM (expired token, never-valid token, IAM revocation).\nTest coverage: tests/map_http_status_401_is_unavailable enforces current behavior \u2014 would need updating if (a) is chosen.",
  "ephemeral": 0,
  "id": "crate-secretsx-t4vc.2",
  "is_template": 0,
  "issue_type": "task",
  "metadata": {},
  "no_history": 0,
  "owner": "mark@reviewcommit.com",
  "pinned": 0,
  "priority": 1,
  "status": "closed",
  "timeout_ns": 0,
  "title": "401 -> Unavailable conflicts with secretx-core contract semantics",
  "updated_at": "2026-06-16T15:02:23Z",
  "dependencies": [
    {
      "created_at": "2026-05-07T18:34:48Z",
      "created_by": "Mark Atwood",
      "depends_on_id": "crate-secretsx-t4vc",
      "metadata": {},
      "type": "parent-child"
    }
  ]
}
