{
  "id": "crate-secretsx-jwg.11",
  "title": "pkcs11: ECDSA algorithm detection hardcodes P-256 without curve inspection",
  "description": "secretx-pkcs11/src/lib.rs detect_algorithm() returns EcdsaP256Sha256 for any ECDSA key without reading the EC_PARAMS attribute to determine the actual curve. Trigger: PKCS#11 token with a P-384 or secp256k1 key \u2192 algorithm() returns EcdsaP256Sha256 \u2192 signature verification fails (or succeeds spuriously with wrong curve). Will silently produce wrong results for any non-P256 ECDSA key.",
  "status": "closed",
  "priority": 1,
  "issue_type": "bug",
  "assignee": "Mark Atwood",
  "created_by": "Mark Atwood",
  "created_at": "2026-04-23T21:08:40Z",
  "updated_at": "2026-04-23T21:32:02Z",
  "closed_at": "2026-04-23T21:32:02Z",
  "dependencies": [
    {
      "depends_on_id": "crate-secretsx-jwg",
      "dep_type": "parent_child",
      "created_by": "Mark Atwood",
      "created_at": "2026-04-23 14:08:39"
    }
  ]
}
