{
  "id": "crate-secretsx-xfi.4",
  "title": "map_put_error: 404 on write is mount-not-found, not NotFound \u2014 correct semantic split",
  "description": "Why this choice is correct: Vault KV v2 write (POST /data/<path>) creates the secret at any path under a valid mount. A 404 on write means the mount doesn't exist, not the path. Returning NotFound (the SecretError variant for 'secret doesn't exist') would be a category error \u2014 callers use NotFound to decide whether to create a secret, and returning it on a bad mount would silently mislead them.\n\nWhat a contributor might suggest: unify the two error mappers into one (DRY). This is wrong: the 404 semantics differ between read and write operations on KV v2. The duplication is load-bearing. The docstring on map_put_error explains why.",
  "status": "closed",
  "priority": 3,
  "issue_type": "decision",
  "created_by": "Mark Atwood",
  "created_at": "2026-04-24T05:34:34Z",
  "updated_at": "2026-04-24T05:37:37Z",
  "closed_at": "2026-04-24T05:37:37Z",
  "dependencies": [
    {
      "depends_on_id": "crate-secretsx-xfi",
      "dep_type": "parent_child",
      "created_by": "Mark Atwood",
      "created_at": "2026-04-23T22:34:33Z"
    }
  ]
}
