{
  "assignee": "Mark Atwood",
  "close_reason": "Closed",
  "closed_at": "2026-06-16T15:06:01Z",
  "compaction_level": 0,
  "content_hash": "5ba2cfa07c7fad450d8b00677021bb59451cf009a82d3ff6ee2b4e7980cab390",
  "created_at": "2026-05-08T01:21:55Z",
  "created_by": "Mark Atwood",
  "description": "secretx-file/src/lib.rs:78 uses std::fs::read which pre-sizes via metadata().len() but falls back to growing the Vec when len is 0 or unknown (e.g., procfs files, named pipes, character devices, sysfs). Each grow doubles capacity and the old allocation is freed without zeroization \u2014 secret bytes from the partial read remain in the heap until overwritten by another allocator request. SecretValue's Zeroizing wrapper protects only the FINAL Vec. Trigger: secretx:file:/proc/self/cmdline or any pseudo-file with metadata.len()==0 reporting actual content. Fix: use File::open + metadata + read into a Zeroizing<Vec<u8>>::with_capacity(size), or document that file sources must be regular files with accurate size.",
  "ephemeral": 0,
  "id": "crate-secretsx-qth2.3",
  "is_template": 0,
  "issue_type": "bug",
  "metadata": {},
  "no_history": 0,
  "owner": "mark@reviewcommit.com",
  "pinned": 0,
  "priority": 1,
  "status": "closed",
  "timeout_ns": 0,
  "title": "[bug] std::fs::read may grow Vec, leaving secret bytes in deallocated buffers (no zeroize)",
  "updated_at": "2026-06-16T15:06:01Z",
  "dependencies": [
    {
      "created_at": "2026-05-07T18:21:54Z",
      "created_by": "Mark Atwood",
      "depends_on_id": "crate-secretsx-qth2",
      "metadata": {},
      "type": "parent-child"
    }
  ]
}
