{
  "close_reason": "Design decision: split_once preserves nested paths",
  "closed_at": "2026-06-16T18:28:05Z",
  "compaction_level": 0,
  "content_hash": "bc75365407fb1f912f33942b88df97a2976eb97cc37a8282ab22dd801999be3d",
  "created_at": "2026-05-08T02:04:42Z",
  "created_by": "Mark Atwood",
  "description": "secretx-keyring/src/lib.rs:74-80: `parsed.path().split_once('/')` (using `split_once` instead of `split('/')`) means that for `secretx:keyring:svc/user/sub`, `service` = `svc` and `account` = `user/sub`. This is tested at lib.rs:215-221 (`from_uri_ok_nested_account`).\n\nThis is the right call: the account-side namespace is opaque to the URI scheme, and many real-world secret naming schemes use slash-delimited paths (`org/project/credential`). `split('/')` would either need an arbitrary join-back step or would force users to URL-encode slashes in account names.\n\nA contributor or reviewer might suggest 'just use split('/') and assert exactly two components' \u2014 that would silently regress the nested-account test and break any caller using slashes in account names. Defend the `split_once` choice with the test and the comment at lib.rs:75-76.",
  "ephemeral": 0,
  "id": "crate-secretsx-t2qi.16",
  "is_template": 0,
  "issue_type": "decision",
  "metadata": {},
  "no_history": 0,
  "owner": "mark@reviewcommit.com",
  "pinned": 0,
  "priority": 3,
  "status": "closed",
  "timeout_ns": 0,
  "title": "Decision: split_once('/') for service/account preserves nested paths in account",
  "updated_at": "2026-06-16T18:28:05Z",
  "dependencies": [
    {
      "created_at": "2026-05-07T19:04:42Z",
      "created_by": "Mark Atwood",
      "depends_on_id": "crate-secretsx-t2qi",
      "metadata": {},
      "type": "parent-child"
    }
  ]
}
