{
  "assignee": "Mark Atwood",
  "close_reason": "Closed",
  "closed_at": "2026-06-16T21:35:10Z",
  "compaction_level": 0,
  "content_hash": "a189199f579ec3d1b8e30c8f40c4297f12498f962feca7ba19945f976154f984",
  "created_at": "2026-06-16T21:30:56Z",
  "created_by": "Mark Atwood",
  "description": "The crate-level doc (lines 39-41) and all three try_sign doc comments (Ed25519Signer line 142, EcdsaP256Signer line 200, RsaPssSigner line 266) state: 'Each call creates a scoped thread with a current-thread tokio runtime.' This is false for the non-runtime code path. In sign_sync (lib.rs:64-73), when Handle::try_current().is_err() the function returns immediately after block_on on the calling thread \u2014 no thread is spawned at all. Only the async-runtime path (lines 75-93) spawns a scoped thread. A caller relying on the documented thread-isolation guarantee (e.g. for stack depth, thread-local state, or cancellation isolation) will be wrong in the common sync caller case. Fix: change the doc to accurately describe both paths: 'If called within a tokio runtime, spawns a scoped thread; otherwise runs on the calling thread.'",
  "ephemeral": 0,
  "id": "crate-secretsx-9u54.1",
  "is_template": 0,
  "issue_type": "bug",
  "metadata": {},
  "no_history": 0,
  "owner": "mark@wolfssl.com",
  "pinned": 0,
  "priority": 0,
  "status": "closed",
  "timeout_ns": 0,
  "title": "sign_sync doc claims scoped thread always; non-runtime path runs inline",
  "updated_at": "2026-06-16T21:35:10Z",
  "dependencies": [
    {
      "created_at": "2026-06-16T14:30:55Z",
      "created_by": "Mark Atwood",
      "depends_on_id": "crate-secretsx-9u54",
      "metadata": {},
      "type": "parent-child"
    }
  ]
}
