{
  "assignee": "Mark Atwood",
  "close_reason": "Closed",
  "closed_at": "2026-06-16T15:47:08Z",
  "compaction_level": 0,
  "content_hash": "52cff9e9a5cb248b0175595ab3320b39e35a52af3a94045092ebb0ce424cd557",
  "created_at": "2026-05-08T00:36:25Z",
  "created_by": "Mark Atwood",
  "description": "src/lib.rs:319-325: 'std::str::from_utf8(value.as_bytes()).map(str::to_owned).map_err(|_| SecretError::DecodeFailed(\"Azure Key Vault secrets must be valid UTF-8 strings\".into()))'\n\nIssue 1: the Utf8Error source is dropped via '|_|', so callers get no byte offset and no info about where the input went bad. Diagnostics for binary-input footguns are degraded.\n\nIssue 2: SecretError::DecodeFailed is documented as 'Secret was present but could not be decoded as expected' \u2014 i.e. for decoding *retrieved* secrets, not for input validation in put(). Using it for input rejection is a category error.\n\nFix: include the Utf8Error in the message ('invalid UTF-8 at byte {n}: {e}') and keep DecodeFailed if you accept the slight stretch of meaning, or introduce a more appropriate variant. At minimum, preserve the byte offset.",
  "ephemeral": 0,
  "id": "crate-secretsx-bdu0.5",
  "is_template": 0,
  "issue_type": "task",
  "metadata": {},
  "no_history": 0,
  "owner": "mark@reviewcommit.com",
  "pinned": 0,
  "priority": 1,
  "status": "closed",
  "timeout_ns": 0,
  "title": "put() UTF-8 validation discards Utf8Error source and uses wrong error variant",
  "updated_at": "2026-06-16T15:47:08Z",
  "dependencies": [
    {
      "created_at": "2026-05-07T17:36:25Z",
      "created_by": "Mark Atwood",
      "depends_on_id": "crate-secretsx-bdu0",
      "metadata": {},
      "type": "parent-child"
    }
  ]
}
