{
  "close_reason": "Extracted 6 duplicated helpers into shared mock_helpers module",
  "closed_at": "2026-06-16T18:10:57Z",
  "compaction_level": 0,
  "content_hash": "5b20fafbffa031cfc378b40b76675e8dfbf915971a688128b7c6c633979235a8",
  "created_at": "2026-05-08T01:52:28Z",
  "created_by": "Mark Atwood",
  "description": "secretx-k8s/src/lib.rs:386-447 and 573-634. Six helpers (make_pair, make_backend, respond, secret_json, not_found_json, forbidden_json) are duplicated identically in two test modules. Idiomatic Rust would put them in a single #[cfg(test)] mod test_helpers used by both test mods via 'use super::test_helpers::*;'. Maintenance cost: any change to mock shape (e.g. asserting request bodies \u2014 see issue 5) must be applied twice and will drift.",
  "ephemeral": 0,
  "id": "crate-secretsx-74dj.20",
  "is_template": 0,
  "issue_type": "chore",
  "metadata": {},
  "no_history": 0,
  "owner": "mark@reviewcommit.com",
  "pinned": 0,
  "priority": 2,
  "status": "closed",
  "timeout_ns": 0,
  "title": "Mock test helpers duplicated verbatim between get_mock_tests and put_mock_tests",
  "updated_at": "2026-06-16T18:10:57Z",
  "dependencies": [
    {
      "created_at": "2026-05-07T18:52:28Z",
      "created_by": "Mark Atwood",
      "depends_on_id": "crate-secretsx-74dj",
      "metadata": {},
      "type": "parent-child"
    }
  ]
}
