{
  "close_reason": "Fixed all five findings",
  "closed_at": "2026-06-16T23:04:54Z",
  "compaction_level": 0,
  "content_hash": "3009448a205ae61eb016307778a74d447065ae32cc3179f8f685cb55d6f1727f",
  "created_at": "2026-06-16T23:01:58Z",
  "created_by": "Mark Atwood",
  "description": "lib.rs:268 \u2014 test 'remove_zeroes_and_returns_true' claims to verify zeroing, but only checks the boolean return. The zeroize guarantee comes from Zeroizing<Vec<u8>>'s Drop impl, which this test does not exercise or observe. Either rename to 'remove_returns_true_then_false' to match what it actually tests, or drop the 'zeroes' claim from the name entirely. The zeroing property is structural (type-level) and not something a unit test can easily verify at runtime, so the honest fix is just a rename.",
  "ephemeral": 0,
  "id": "crate-secretsx-fk09.3",
  "is_template": 0,
  "issue_type": "task",
  "metadata": {},
  "no_history": 0,
  "owner": "mark@wolfssl.com",
  "pinned": 0,
  "priority": 3,
  "status": "closed",
  "timeout_ns": 0,
  "title": "Test name overpromises: remove_zeroes_and_returns_true",
  "updated_at": "2026-06-16T23:04:54Z",
  "dependencies": [
    {
      "created_at": "2026-06-16T16:01:58Z",
      "created_by": "Mark Atwood",
      "depends_on_id": "crate-secretsx-fk09",
      "metadata": {},
      "type": "parent-child"
    }
  ]
}
