{
  "id": "crate-secretsx-pjwm",
  "title": "Review: keyring backend implementation",
  "status": "closed",
  "priority": 1,
  "issue_type": "epic",
  "assignee": "Mark Atwood",
  "created_by": "Mark Atwood",
  "created_at": "2026-04-28T21:51:21Z",
  "updated_at": "2026-04-28T22:12:49Z",
  "closed_at": "2026-04-28T22:12:49Z",
  "notes": "Maintainer risk: LOW \u2014 UTF-8 restriction is documented, error messages are clear, the only real risk is the stale headless doc misleading future contributors\nConfidence: 10% chance of missed bug. Least confident: keyring::Error variants \u2014 did not exhaustively verify which error types keyring crate can return for set_password. Uncertainty driven by: not reading keyring crate source. Would raise confidence if: grep keyring source for all Error variants returned by set_password.\nIdiom rating: CLEAN \u2014 no unwraps in prod code, spawn_blocking used correctly, UTF-8 check placed optimally, split_once is a minor improvement"
}
